breath_api_interface/__init__.py
breath_api_interface/proxy.py
breath_api_interface/queue.py
breath_api_interface/request.py
breath_api_interface/service_interface/__init__.py
breath_api_interface/service_interface/service.py
breath_api_interface-0.0.3.dist-info/LICENSE
breath_api_interface-0.0.3.dist-info/METADATA
breath_api_interface-0.0.3.dist-info/WHEEL
breath_api_interface-0.0.3.dist-info/top_level.txt
breath_api_interface-0.0.3.dist-info/RECORD
