Metadata-Version: 2.1
Name: breath-api-interface
Version: 0.0.3
Summary: API interface for creating BReATH services
Home-page: https://gitlab.com/EltonCN/breath-brazilian-research-of-atmosphere-towards-health
Author: EltonCN, João Bonucci, Lucas Araújo, Thiago Lacerda
Author-email: elton.nascimento@students.ic.unicamp.br, j218733@dac.unicamp.br, l240106@dac.unicamp.br, t244712@dac.unicamp.br
License: MIT
Project-URL: Bug Tracker, https://github.com/BReATH-Brazilian-Research/breath_api_interface/issues
Project-URL: Documentation, https://gitlab.com/EltonCN/breath-brazilian-research-of-atmosphere-towards-health/-/wikis/Home
Platform: UNKNOWN
Classifier: Programming Language :: Python :: 3
Classifier: License :: OSI Approved :: MIT License
Requires-Python: >=3.8
License-File: LICENSE
